cygl/__init__.py
cygl/legacy.cpython-312-darwin.so
cygl-1.0a0.dist-info/LICENSE
cygl-1.0a0.dist-info/METADATA
cygl-1.0a0.dist-info/WHEEL
cygl-1.0a0.dist-info/top_level.txt
cygl-1.0a0.dist-info/RECORD
